poppy_ergo_jr/__init__.py
poppy_ergo_jr/_version.py
poppy_ergo_jr/poppy_ergo_jr.py
poppy_ergo_jr/poppy_ergo_jr.urdf
poppy_ergo_jr/configuration/poppy_ergo_jr.json
poppy_ergo_jr/primitives/How_to_add_primitive_FR.py
poppy_ergo_jr/primitives/__init__.py
poppy_ergo_jr/primitives/dance.py
poppy_ergo_jr/primitives/face_tracking.py
poppy_ergo_jr/primitives/headfollow.py
poppy_ergo_jr/primitives/jump.py
poppy_ergo_jr/primitives/postures.py
poppy_ergo_jr/primitives/tracking_feedback.py
poppy_ergo_jr/vrep-scene/poppy_ergo_jr.ttt
poppy_ergo_jr/vrep-scene/poppy_ergo_jr_empty.ttt
poppy_ergo_jr/vrep-scene/poppy_ergo_jr_holder.ttt
poppy_ergo_jr-4.0.2.dist-info/LICENSE
poppy_ergo_jr-4.0.2.dist-info/METADATA
poppy_ergo_jr-4.0.2.dist-info/WHEEL
poppy_ergo_jr-4.0.2.dist-info/top_level.txt
poppy_ergo_jr-4.0.2.dist-info/RECORD
