Metadata-Version: 2.1
Name: poppy-ergo-jr
Version: 4.0.2
Summary: Poppy Ergo Jr Software Library
Home-page: https://poppy-project.org
Author: Poppy Station
Author-email: dev@poppy-station.org
License: GNU GENERAL PUBLIC LICENSE Version 3
License-File: LICENSE
Requires-Dist: pypot (>=4.0.0)
Requires-Dist: hampy (>=1.4.2)
